perspective/__init__.py
perspective/blocking.py
perspective/models.py
perspectiveapi-1.1.0.dist-info/METADATA
perspectiveapi-1.1.0.dist-info/WHEEL
perspectiveapi-1.1.0.dist-info/licenses/LICENSE
perspectiveapi-1.1.0.dist-info/RECORD
