Metadata-Version: 2.3
Name: perspectiveapi
Version: 1.1.0
Summary: a python wrapper for google's perspective api
Author-email: te <thrzl@icloud.com>
License-File: LICENSE
Requires-Python: >=3.8
Requires-Dist: httpx>=0.27.0
